Metadata-Version: 1.1
Name: amqpclient
Version: 0.1.0
Summary: Simple AMQP python CLI applications for receiving/sending
Home-page: https://github.com/okurz/amqpclient
Author: Oliver kurz
Author-email: okurz@suse.com
License: MIT
Keywords: script helper AMQP CLI text console
Platform: UNKNOWN
Classifier: Development Status :: 3 - Alpha
Classifier: Topic :: Utilities
Classifier: License :: OSI Approved :: MIT License
